{"_etl_version":"0.1.0","_source":"ISTAT - Matrice pendolarismo per lavoro 2021","_source_url":"https://esploradati.istat.it/databrowser/DWL/PERMPOP/MATPEN/matrix_pendoLAVORO_2021.zip","_license":"CC BY 3.0 IT","_anno_rilevazione":2021,"_motivo_spostamento":"lavoro","_generated_at":"2026-05-16T14:52:45+00:00","kpi":{"uscenti_totali":1038,"entranti_totali":737,"saldo_netto":-301,"auto_contenimento_pct":16.1,"n_destinazioni":95,"n_origini":88,"top_destinazioni":[{"istat":"001125","count":476},{"istat":"001272","count":76},{"istat":"001269","count":43},{"istat":"001042","count":40},{"istat":"001020","count":34},{"istat":"001092","count":20},{"istat":"001027","count":17},{"istat":"001047","count":15},{"istat":"001082","count":15},{"istat":"001223","count":14}],"top_origini":[{"istat":"001125","count":191},{"istat":"001020","count":67},{"istat":"001269","count":36},{"istat":"001066","count":32},{"istat":"001235","count":29},{"istat":"001160","count":24},{"istat":"001030","count":22},{"istat":"001132","count":17},{"istat":"001223","count":16},{"istat":"001137","count":13}]}}