{"_etl_version":"0.1.0","_source":"ISTAT - Matrice pendolarismo per lavoro 2021","_source_url":"https://esploradati.istat.it/databrowser/DWL/PERMPOP/MATPEN/matrix_pendoLAVORO_2021.zip","_license":"CC BY 3.0 IT","_anno_rilevazione":2021,"_motivo_spostamento":"lavoro","_generated_at":"2026-05-16T14:52:45+00:00","kpi":{"uscenti_totali":6468,"entranti_totali":7879,"saldo_netto":1411,"auto_contenimento_pct":15.8,"n_destinazioni":161,"n_origini":250,"top_destinazioni":[{"istat":"001272","count":2493},{"istat":"001171","count":723},{"istat":"001219","count":428},{"istat":"001120","count":367},{"istat":"001090","count":260},{"istat":"001024","count":252},{"istat":"001156","count":184},{"istat":"001038","count":169},{"istat":"001164","count":121},{"istat":"001315","count":92}],"top_origini":[{"istat":"001272","count":2289},{"istat":"001171","count":555},{"istat":"001194","count":467},{"istat":"001164","count":341},{"istat":"001219","count":308},{"istat":"001156","count":271},{"istat":"001038","count":218},{"istat":"001315","count":211},{"istat":"001090","count":206},{"istat":"001120","count":197}]}}