{"_etl_version":"0.1.0","_source":"ISTAT - Matrice pendolarismo per lavoro 2021","_source_url":"https://esploradati.istat.it/databrowser/DWL/PERMPOP/MATPEN/matrix_pendoLAVORO_2021.zip","_license":"CC BY 3.0 IT","_anno_rilevazione":2021,"_motivo_spostamento":"lavoro","_generated_at":"2026-05-16T14:52:45+00:00","kpi":{"uscenti_totali":59,"entranti_totali":50,"saldo_netto":-9,"auto_contenimento_pct":20.3,"n_destinazioni":19,"n_origini":15,"top_destinazioni":[{"istat":"004078","count":9},{"istat":"004166","count":8},{"istat":"004203","count":6},{"istat":"004205","count":6},{"istat":"004122","count":5},{"istat":"004075","count":4},{"istat":"004197","count":4},{"istat":"004237","count":4},{"istat":"004217","count":2},{"istat":"004244","count":2}],"top_origini":[{"istat":"004122","count":7},{"istat":"004033","count":6},{"istat":"004205","count":6},{"istat":"004075","count":5},{"istat":"004237","count":5},{"istat":"004116","count":4},{"istat":"004017","count":3},{"istat":"004034","count":3},{"istat":"004166","count":3},{"istat":"004197","count":2}]}}