{"_etl_version":"0.1.0","_source":"ISTAT - Matrice pendolarismo per lavoro 2021","_source_url":"https://esploradati.istat.it/databrowser/DWL/PERMPOP/MATPEN/matrix_pendoLAVORO_2021.zip","_license":"CC BY 3.0 IT","_anno_rilevazione":2021,"_motivo_spostamento":"lavoro","_generated_at":"2026-05-16T14:52:45+00:00","kpi":{"uscenti_totali":258,"entranti_totali":31,"saldo_netto":-227,"auto_contenimento_pct":12.2,"n_destinazioni":48,"n_origini":14,"top_destinazioni":[{"istat":"001272","count":62},{"istat":"001078","count":54},{"istat":"001009","count":23},{"istat":"005031","count":14},{"istat":"001197","count":7},{"istat":"001257","count":7},{"istat":"005118","count":6},{"istat":"001012","count":5},{"istat":"001048","count":5},{"istat":"001156","count":5}],"top_origini":[{"istat":"005031","count":8},{"istat":"001078","count":6},{"istat":"001272","count":3},{"istat":"001156","count":2},{"istat":"001158","count":2},{"istat":"005012","count":2},{"istat":"001018","count":1},{"istat":"001047","count":1},{"istat":"001060","count":1},{"istat":"001163","count":1}]}}