{"_etl_version":"0.1.0","_source":"ISTAT - Matrice pendolarismo per lavoro 2021","_source_url":"https://esploradati.istat.it/databrowser/DWL/PERMPOP/MATPEN/matrix_pendoLAVORO_2021.zip","_license":"CC BY 3.0 IT","_anno_rilevazione":2021,"_motivo_spostamento":"lavoro","_generated_at":"2026-05-16T14:52:45+00:00","kpi":{"uscenti_totali":21,"entranti_totali":3,"saldo_netto":-18,"auto_contenimento_pct":19.2,"n_destinazioni":9,"n_origini":3,"top_destinazioni":[{"istat":"006174","count":5},{"istat":"018182","count":5},{"istat":"006053","count":3},{"istat":"010025","count":2},{"istat":"018110","count":2},{"istat":"006040","count":1},{"istat":"006079","count":1},{"istat":"006181","count":1},{"istat":"015011","count":1}],"top_origini":[{"istat":"006155","count":1},{"istat":"006174","count":1},{"istat":"006181","count":1}]}}