{"_etl_version":"0.1.0","_source":"ISTAT - Matrice pendolarismo per lavoro 2021","_source_url":"https://esploradati.istat.it/databrowser/DWL/PERMPOP/MATPEN/matrix_pendoLAVORO_2021.zip","_license":"CC BY 3.0 IT","_anno_rilevazione":2021,"_motivo_spostamento":"lavoro","_generated_at":"2026-05-16T14:52:45+00:00","kpi":{"uscenti_totali":306,"entranti_totali":462,"saldo_netto":156,"auto_contenimento_pct":28.5,"n_destinazioni":46,"n_origini":64,"top_destinazioni":[{"istat":"007052","count":66},{"istat":"007003","count":40},{"istat":"007073","count":34},{"istat":"007004","count":24},{"istat":"007009","count":15},{"istat":"007065","count":15},{"istat":"007023","count":12},{"istat":"007020","count":10},{"istat":"007054","count":10},{"istat":"007007","count":8}],"top_origini":[{"istat":"007052","count":65},{"istat":"007023","count":50},{"istat":"001030","count":32},{"istat":"007073","count":25},{"istat":"007037","count":24},{"istat":"001125","count":22},{"istat":"001266","count":20},{"istat":"007004","count":20},{"istat":"007043","count":17},{"istat":"001271","count":15}]}}