{"_etl_version":"0.1.0","_source":"ISTAT - Matrice pendolarismo per lavoro 2021","_source_url":"https://esploradati.istat.it/databrowser/DWL/PERMPOP/MATPEN/matrix_pendoLAVORO_2021.zip","_license":"CC BY 3.0 IT","_anno_rilevazione":2021,"_motivo_spostamento":"lavoro","_generated_at":"2026-05-16T14:52:45+00:00","kpi":{"uscenti_totali":101,"entranti_totali":75,"saldo_netto":-26,"auto_contenimento_pct":21.1,"n_destinazioni":15,"n_origini":22,"top_destinazioni":[{"istat":"011017","count":19},{"istat":"011015","count":13},{"istat":"011006","count":10},{"istat":"011019","count":10},{"istat":"011007","count":8},{"istat":"010059","count":7},{"istat":"011005","count":6},{"istat":"011012","count":6},{"istat":"010025","count":5},{"istat":"011028","count":4}],"top_origini":[{"istat":"011017","count":11},{"istat":"011028","count":8},{"istat":"011006","count":7},{"istat":"011003","count":5},{"istat":"011007","count":5},{"istat":"010011","count":4},{"istat":"010059","count":4},{"istat":"011009","count":4},{"istat":"011014","count":4},{"istat":"011018","count":4}]}}