{"_etl_version":"0.1.0","_source":"ISTAT - Matrice pendolarismo per lavoro 2021","_source_url":"https://esploradati.istat.it/databrowser/DWL/PERMPOP/MATPEN/matrix_pendoLAVORO_2021.zip","_license":"CC BY 3.0 IT","_anno_rilevazione":2021,"_motivo_spostamento":"lavoro","_generated_at":"2026-05-16T14:52:45+00:00","kpi":{"uscenti_totali":589,"entranti_totali":468,"saldo_netto":-121,"auto_contenimento_pct":25.6,"n_destinazioni":79,"n_origini":60,"top_destinazioni":[{"istat":"012133","count":112},{"istat":"012086","count":75},{"istat":"012092","count":49},{"istat":"012027","count":45},{"istat":"012060","count":32},{"istat":"012059","count":27},{"istat":"015146","count":23},{"istat":"012113","count":19},{"istat":"012131","count":16},{"istat":"012083","count":12}],"top_origini":[{"istat":"012059","count":96},{"istat":"012060","count":43},{"istat":"012027","count":42},{"istat":"012086","count":37},{"istat":"012133","count":23},{"istat":"012092","count":18},{"istat":"012131","count":17},{"istat":"012024","count":16},{"istat":"012099","count":11},{"istat":"012069","count":8}]}}