{"_etl_version":"0.1.0","_source":"ISTAT - Matrice pendolarismo per lavoro 2021","_source_url":"https://esploradati.istat.it/databrowser/DWL/PERMPOP/MATPEN/matrix_pendoLAVORO_2021.zip","_license":"CC BY 3.0 IT","_anno_rilevazione":2021,"_motivo_spostamento":"lavoro","_generated_at":"2026-05-16T14:52:45+00:00","kpi":{"uscenti_totali":1321,"entranti_totali":2675,"saldo_netto":1354,"auto_contenimento_pct":15.4,"n_destinazioni":134,"n_origini":280,"top_destinazioni":[{"istat":"015146","count":395},{"istat":"015142","count":128},{"istat":"015205","count":85},{"istat":"015237","count":68},{"istat":"015175","count":60},{"istat":"015070","count":36},{"istat":"015210","count":36},{"istat":"015171","count":30},{"istat":"015185","count":29},{"istat":"015060","count":25}],"top_origini":[{"istat":"015146","count":234},{"istat":"015142","count":218},{"istat":"015175","count":111},{"istat":"015210","count":96},{"istat":"015205","count":84},{"istat":"015224","count":84},{"istat":"015237","count":79},{"istat":"015178","count":74},{"istat":"019084","count":72},{"istat":"015070","count":63}]}}