{"_etl_version":"0.1.0","_source":"ISTAT - Matrice pendolarismo per lavoro 2021","_source_url":"https://esploradati.istat.it/databrowser/DWL/PERMPOP/MATPEN/matrix_pendoLAVORO_2021.zip","_license":"CC BY 3.0 IT","_anno_rilevazione":2021,"_motivo_spostamento":"lavoro","_generated_at":"2026-05-16T14:52:45+00:00","kpi":{"uscenti_totali":223,"entranti_totali":116,"saldo_netto":-107,"auto_contenimento_pct":44.7,"n_destinazioni":31,"n_origini":17,"top_destinazioni":[{"istat":"016243","count":75},{"istat":"016195","count":18},{"istat":"016024","count":15},{"istat":"016077","count":15},{"istat":"016017","count":10},{"istat":"016070","count":9},{"istat":"016064","count":7},{"istat":"017065","count":7},{"istat":"016144","count":6},{"istat":"016182","count":6}],"top_origini":[{"istat":"016243","count":33},{"istat":"016195","count":32},{"istat":"016064","count":14},{"istat":"016017","count":10},{"istat":"016187","count":6},{"istat":"017006","count":6},{"istat":"016077","count":4},{"istat":"015170","count":2},{"istat":"015059","count":1},{"istat":"015146","count":1}]}}