{"_etl_version":"0.1.0","_source":"ISTAT - Matrice pendolarismo per lavoro 2021","_source_url":"https://esploradati.istat.it/databrowser/DWL/PERMPOP/MATPEN/matrix_pendoLAVORO_2021.zip","_license":"CC BY 3.0 IT","_anno_rilevazione":2021,"_motivo_spostamento":"lavoro","_generated_at":"2026-05-16T14:52:45+00:00","kpi":{"uscenti_totali":302,"entranti_totali":254,"saldo_netto":-48,"auto_contenimento_pct":26.2,"n_destinazioni":47,"n_origini":28,"top_destinazioni":[{"istat":"016125","count":50},{"istat":"016024","count":44},{"istat":"016190","count":32},{"istat":"016188","count":16},{"istat":"016227","count":13},{"istat":"016246","count":12},{"istat":"016036","count":10},{"istat":"016145","count":9},{"istat":"016132","count":8},{"istat":"016239","count":7}],"top_origini":[{"istat":"016188","count":40},{"istat":"016190","count":30},{"istat":"016246","count":20},{"istat":"016125","count":19},{"istat":"016191","count":17},{"istat":"016145","count":12},{"istat":"016184","count":11},{"istat":"016036","count":10},{"istat":"016229","count":9},{"istat":"016253","count":9}]}}