{"_etl_version":"0.1.0","_source":"ISTAT - Matrice pendolarismo per lavoro 2021","_source_url":"https://esploradati.istat.it/databrowser/DWL/PERMPOP/MATPEN/matrix_pendoLAVORO_2021.zip","_license":"CC BY 3.0 IT","_anno_rilevazione":2021,"_motivo_spostamento":"lavoro","_generated_at":"2026-05-16T14:52:45+00:00","kpi":{"uscenti_totali":3371,"entranti_totali":1483,"saldo_netto":-1888,"auto_contenimento_pct":30.1,"n_destinazioni":169,"n_origini":133,"top_destinazioni":[{"istat":"017029","count":1040},{"istat":"017088","count":263},{"istat":"017103","count":195},{"istat":"017078","count":138},{"istat":"017072","count":131},{"istat":"017173","count":127},{"istat":"017147","count":123},{"istat":"017113","count":81},{"istat":"017114","count":81},{"istat":"017021","count":56}],"top_origini":[{"istat":"017088","count":201},{"istat":"017029","count":196},{"istat":"017078","count":105},{"istat":"017103","count":102},{"istat":"017114","count":79},{"istat":"017147","count":78},{"istat":"017122","count":46},{"istat":"017066","count":40},{"istat":"017072","count":37},{"istat":"017037","count":34}]}}