{"_etl_version":"0.1.0","_source":"ISTAT - Matrice pendolarismo per lavoro 2021","_source_url":"https://esploradati.istat.it/databrowser/DWL/PERMPOP/MATPEN/matrix_pendoLAVORO_2021.zip","_license":"CC BY 3.0 IT","_anno_rilevazione":2021,"_motivo_spostamento":"lavoro","_generated_at":"2026-05-16T14:52:45+00:00","kpi":{"uscenti_totali":318,"entranti_totali":96,"saldo_netto":-222,"auto_contenimento_pct":20.5,"n_destinazioni":53,"n_origini":22,"top_destinazioni":[{"istat":"018182","count":125},{"istat":"015146","count":23},{"istat":"018110","count":20},{"istat":"018033","count":11},{"istat":"018095","count":11},{"istat":"018138","count":9},{"istat":"018037","count":7},{"istat":"018054","count":7},{"istat":"018084","count":7},{"istat":"006003","count":6}],"top_origini":[{"istat":"018182","count":45},{"istat":"018011","count":8},{"istat":"018054","count":6},{"istat":"018149","count":5},{"istat":"018033","count":4},{"istat":"018108","count":4},{"istat":"018037","count":3},{"istat":"006053","count":2},{"istat":"006132","count":2},{"istat":"018023","count":2}]}}