{"_etl_version":"0.1.0","_source":"ISTAT - Matrice pendolarismo per lavoro 2021","_source_url":"https://esploradati.istat.it/databrowser/DWL/PERMPOP/MATPEN/matrix_pendoLAVORO_2021.zip","_license":"CC BY 3.0 IT","_anno_rilevazione":2021,"_motivo_spostamento":"lavoro","_generated_at":"2026-05-16T14:52:45+00:00","kpi":{"uscenti_totali":263,"entranti_totali":34,"saldo_netto":-229,"auto_contenimento_pct":13.2,"n_destinazioni":57,"n_origini":13,"top_destinazioni":[{"istat":"018102","count":54},{"istat":"018177","count":28},{"istat":"015146","count":19},{"istat":"018059","count":16},{"istat":"018088","count":12},{"istat":"018109","count":12},{"istat":"018110","count":11},{"istat":"018168","count":11},{"istat":"006003","count":9},{"istat":"018039","count":8}],"top_origini":[{"istat":"018059","count":7},{"istat":"018168","count":7},{"istat":"018144","count":4},{"istat":"018050","count":2},{"istat":"018102","count":2},{"istat":"018123","count":2},{"istat":"018146","count":2},{"istat":"018164","count":2},{"istat":"018172","count":2},{"istat":"002158","count":1}]}}