{"_etl_version":"0.1.0","_source":"ISTAT - Matrice pendolarismo per lavoro 2021","_source_url":"https://esploradati.istat.it/databrowser/DWL/PERMPOP/MATPEN/matrix_pendoLAVORO_2021.zip","_license":"CC BY 3.0 IT","_anno_rilevazione":2021,"_motivo_spostamento":"lavoro","_generated_at":"2026-05-16T14:52:45+00:00","kpi":{"uscenti_totali":317,"entranti_totali":158,"saldo_netto":-159,"auto_contenimento_pct":18.5,"n_destinazioni":41,"n_origini":38,"top_destinazioni":[{"istat":"019036","count":161},{"istat":"019076","count":20},{"istat":"019095","count":14},{"istat":"015146","count":13},{"istat":"019026","count":11},{"istat":"019098","count":10},{"istat":"019038","count":9},{"istat":"019100","count":9},{"istat":"019051","count":6},{"istat":"019065","count":5}],"top_origini":[{"istat":"019036","count":28},{"istat":"019095","count":24},{"istat":"019051","count":15},{"istat":"019076","count":14},{"istat":"019003","count":10},{"istat":"019038","count":8},{"istat":"019100","count":6},{"istat":"019025","count":5},{"istat":"019026","count":5},{"istat":"019097","count":4}]}}