{"_etl_version":"0.1.0","_source":"ISTAT - Matrice pendolarismo per lavoro 2021","_source_url":"https://esploradati.istat.it/databrowser/DWL/PERMPOP/MATPEN/matrix_pendoLAVORO_2021.zip","_license":"CC BY 3.0 IT","_anno_rilevazione":2021,"_motivo_spostamento":"lavoro","_generated_at":"2026-05-16T14:52:45+00:00","kpi":{"uscenti_totali":1246,"entranti_totali":1219,"saldo_netto":-27,"auto_contenimento_pct":51.5,"n_destinazioni":35,"n_origini":17,"top_destinazioni":[{"istat":"021013","count":579},{"istat":"021108","count":181},{"istat":"021034","count":127},{"istat":"021008","count":121},{"istat":"021030","count":38},{"istat":"021011","count":35},{"istat":"021088","count":31},{"istat":"021081","count":30},{"istat":"021021","count":17},{"istat":"021106","count":9}],"top_origini":[{"istat":"021108","count":495},{"istat":"021088","count":197},{"istat":"021034","count":183},{"istat":"021013","count":158},{"istat":"021030","count":39},{"istat":"021081","count":34},{"istat":"021068","count":26},{"istat":"021021","count":22},{"istat":"021106","count":15},{"istat":"021063","count":11}]}}