{"_etl_version":"0.1.0","_source":"ISTAT - Matrice pendolarismo per lavoro 2021","_source_url":"https://esploradati.istat.it/databrowser/DWL/PERMPOP/MATPEN/matrix_pendoLAVORO_2021.zip","_license":"CC BY 3.0 IT","_anno_rilevazione":2021,"_motivo_spostamento":"lavoro","_generated_at":"2026-05-16T14:52:45+00:00","kpi":{"uscenti_totali":1416,"entranti_totali":1108,"saldo_netto":-308,"auto_contenimento_pct":30.8,"n_destinazioni":49,"n_origini":86,"top_destinazioni":[{"istat":"021008","count":846},{"istat":"021004","count":95},{"istat":"021051","count":78},{"istat":"021041","count":55},{"istat":"021055","count":34},{"istat":"021040","count":30},{"istat":"021002","count":25},{"istat":"021015","count":17},{"istat":"021038","count":17},{"istat":"021072","count":17}],"top_origini":[{"istat":"021008","count":188},{"istat":"021004","count":89},{"istat":"021041","count":87},{"istat":"021051","count":82},{"istat":"021055","count":70},{"istat":"021035","count":52},{"istat":"021002","count":50},{"istat":"021050","count":47},{"istat":"021099","count":27},{"istat":"021066","count":26}]}}