{"_etl_version":"0.1.0","_source":"ISTAT - Matrice pendolarismo per lavoro 2021","_source_url":"https://esploradati.istat.it/databrowser/DWL/PERMPOP/MATPEN/matrix_pendoLAVORO_2021.zip","_license":"CC BY 3.0 IT","_anno_rilevazione":2021,"_motivo_spostamento":"lavoro","_generated_at":"2026-05-16T14:52:45+00:00","kpi":{"uscenti_totali":391,"entranti_totali":490,"saldo_netto":99,"auto_contenimento_pct":17.3,"n_destinazioni":23,"n_origini":63,"top_destinazioni":[{"istat":"021008","count":223},{"istat":"021040","count":69},{"istat":"021060","count":23},{"istat":"021029","count":18},{"istat":"021012","count":9},{"istat":"021004","count":7},{"istat":"021015","count":6},{"istat":"021002","count":5},{"istat":"021023","count":5},{"istat":"021097","count":4}],"top_origini":[{"istat":"021040","count":78},{"istat":"021008","count":61},{"istat":"021060","count":38},{"istat":"021029","count":32},{"istat":"021004","count":30},{"istat":"021015","count":30},{"istat":"021051","count":27},{"istat":"021076","count":18},{"istat":"021098","count":17},{"istat":"021012","count":11}]}}