{"_etl_version":"0.1.0","_source":"ISTAT - Matrice pendolarismo per lavoro 2021","_source_url":"https://esploradati.istat.it/databrowser/DWL/PERMPOP/MATPEN/matrix_pendoLAVORO_2021.zip","_license":"CC BY 3.0 IT","_anno_rilevazione":2021,"_motivo_spostamento":"lavoro","_generated_at":"2026-05-16T14:52:45+00:00","kpi":{"uscenti_totali":3562,"entranti_totali":3241,"saldo_netto":-321,"auto_contenimento_pct":24.9,"n_destinazioni":149,"n_origini":169,"top_destinazioni":[{"istat":"026086","count":632},{"istat":"026091","count":542},{"istat":"026050","count":210},{"istat":"026021","count":148},{"istat":"026040","count":147},{"istat":"026008","count":146},{"istat":"026059","count":141},{"istat":"026083","count":129},{"istat":"026002","count":103},{"istat":"026046","count":96}],"top_origini":[{"istat":"026091","count":332},{"istat":"026086","count":316},{"istat":"026040","count":255},{"istat":"026002","count":232},{"istat":"026050","count":165},{"istat":"026059","count":117},{"istat":"026008","count":111},{"istat":"026055","count":98},{"istat":"026005","count":94},{"istat":"026046","count":88}]}}