{"_etl_version":"0.1.0","_source":"ISTAT - Matrice pendolarismo per lavoro 2021","_source_url":"https://esploradati.istat.it/databrowser/DWL/PERMPOP/MATPEN/matrix_pendoLAVORO_2021.zip","_license":"CC BY 3.0 IT","_anno_rilevazione":2021,"_motivo_spostamento":"lavoro","_generated_at":"2026-05-16T14:52:45+00:00","kpi":{"uscenti_totali":1506,"entranti_totali":1266,"saldo_netto":-240,"auto_contenimento_pct":25.0,"n_destinazioni":104,"n_origini":91,"top_destinazioni":[{"istat":"026050","count":205},{"istat":"026046","count":195},{"istat":"026093","count":155},{"istat":"026086","count":132},{"istat":"026082","count":87},{"istat":"026091","count":86},{"istat":"026059","count":56},{"istat":"026062","count":56},{"istat":"026085","count":47},{"istat":"026002","count":46}],"top_origini":[{"istat":"026050","count":191},{"istat":"026093","count":167},{"istat":"026046","count":118},{"istat":"026062","count":109},{"istat":"026002","count":90},{"istat":"026086","count":71},{"istat":"026082","count":59},{"istat":"026085","count":47},{"istat":"026059","count":45},{"istat":"026091","count":41}]}}