{"_etl_version":"0.1.0","_source":"ISTAT - Matrice pendolarismo per lavoro 2021","_source_url":"https://esploradati.istat.it/databrowser/DWL/PERMPOP/MATPEN/matrix_pendoLAVORO_2021.zip","_license":"CC BY 3.0 IT","_anno_rilevazione":2021,"_motivo_spostamento":"lavoro","_generated_at":"2026-05-16T14:52:45+00:00","kpi":{"uscenti_totali":2708,"entranti_totali":2196,"saldo_netto":-512,"auto_contenimento_pct":19.8,"n_destinazioni":156,"n_origini":113,"top_destinazioni":[{"istat":"028060","count":445},{"istat":"027042","count":427},{"istat":"028100","count":210},{"istat":"027012","count":200},{"istat":"027017","count":160},{"istat":"027028","count":122},{"istat":"027039","count":109},{"istat":"027023","count":90},{"istat":"028058","count":89},{"istat":"027035","count":81}],"top_origini":[{"istat":"027004","count":205},{"istat":"027012","count":197},{"istat":"027039","count":167},{"istat":"027043","count":156},{"istat":"027028","count":141},{"istat":"028060","count":140},{"istat":"028100","count":140},{"istat":"027023","count":136},{"istat":"027017","count":114},{"istat":"027003","count":84}]}}