{"_etl_version":"0.1.0","_source":"ISTAT - Matrice pendolarismo per lavoro 2021","_source_url":"https://esploradati.istat.it/databrowser/DWL/PERMPOP/MATPEN/matrix_pendoLAVORO_2021.zip","_license":"CC BY 3.0 IT","_anno_rilevazione":2021,"_motivo_spostamento":"lavoro","_generated_at":"2026-05-16T14:52:45+00:00","kpi":{"uscenti_totali":950,"entranti_totali":1635,"saldo_netto":685,"auto_contenimento_pct":23.6,"n_destinazioni":93,"n_origini":102,"top_destinazioni":[{"istat":"028034","count":176},{"istat":"028060","count":121},{"istat":"028055","count":54},{"istat":"029041","count":49},{"istat":"028094","count":39},{"istat":"028002","count":33},{"istat":"028006","count":33},{"istat":"028003","count":28},{"istat":"028090","count":23},{"istat":"028106","count":22}],"top_origini":[{"istat":"028034","count":218},{"istat":"028002","count":126},{"istat":"028004","count":111},{"istat":"028094","count":84},{"istat":"029041","count":83},{"istat":"028055","count":77},{"istat":"027006","count":65},{"istat":"029044","count":63},{"istat":"028006","count":45},{"istat":"028060","count":45}]}}