{"_etl_version":"0.1.0","_source":"ISTAT - Matrice pendolarismo per lavoro 2021","_source_url":"https://esploradati.istat.it/databrowser/DWL/PERMPOP/MATPEN/matrix_pendoLAVORO_2021.zip","_license":"CC BY 3.0 IT","_anno_rilevazione":2021,"_motivo_spostamento":"lavoro","_generated_at":"2026-05-16T14:52:45+00:00","kpi":{"uscenti_totali":1832,"entranti_totali":1192,"saldo_netto":-640,"auto_contenimento_pct":22.0,"n_destinazioni":116,"n_origini":94,"top_destinazioni":[{"istat":"028060","count":350},{"istat":"028089","count":200},{"istat":"028086","count":115},{"istat":"028071","count":107},{"istat":"028054","count":104},{"istat":"028001","count":98},{"istat":"028072","count":80},{"istat":"028073","count":79},{"istat":"024116","count":76},{"istat":"028092","count":59}],"top_origini":[{"istat":"028089","count":167},{"istat":"028071","count":118},{"istat":"028086","count":97},{"istat":"028073","count":83},{"istat":"028060","count":80},{"istat":"028096","count":79},{"istat":"028001","count":60},{"istat":"028054","count":54},{"istat":"028105","count":45},{"istat":"028072","count":37}]}}