{"_etl_version":"0.1.0","_source":"ISTAT - Matrice pendolarismo per lavoro 2021","_source_url":"https://esploradati.istat.it/databrowser/DWL/PERMPOP/MATPEN/matrix_pendoLAVORO_2021.zip","_license":"CC BY 3.0 IT","_anno_rilevazione":2021,"_motivo_spostamento":"lavoro","_generated_at":"2026-05-16T14:52:45+00:00","kpi":{"uscenti_totali":1923,"entranti_totali":2874,"saldo_netto":951,"auto_contenimento_pct":49.1,"n_destinazioni":150,"n_origini":170,"top_destinazioni":[{"istat":"029041","count":319},{"istat":"023044","count":177},{"istat":"029029","count":138},{"istat":"023020","count":132},{"istat":"023095","count":84},{"istat":"029027","count":83},{"istat":"023091","count":56},{"istat":"029047","count":51},{"istat":"029043","count":47},{"istat":"028049","count":41}],"top_origini":[{"istat":"029029","count":455},{"istat":"029041","count":247},{"istat":"028049","count":182},{"istat":"029027","count":160},{"istat":"023020","count":157},{"istat":"029047","count":102},{"istat":"023044","count":72},{"istat":"028062","count":63},{"istat":"029031","count":63},{"istat":"028029","count":60}]}}