{"_etl_version":"0.1.0","_source":"ISTAT - Matrice pendolarismo per lavoro 2021","_source_url":"https://esploradati.istat.it/databrowser/DWL/PERMPOP/MATPEN/matrix_pendoLAVORO_2021.zip","_license":"CC BY 3.0 IT","_anno_rilevazione":2021,"_motivo_spostamento":"lavoro","_generated_at":"2026-05-16T14:52:45+00:00","kpi":{"uscenti_totali":134,"entranti_totali":10,"saldo_netto":-124,"auto_contenimento_pct":21.2,"n_destinazioni":24,"n_origini":3,"top_destinazioni":[{"istat":"030129","count":29},{"istat":"030116","count":23},{"istat":"030118","count":11},{"istat":"030006","count":9},{"istat":"030052","count":9},{"istat":"030066","count":8},{"istat":"030127","count":6},{"istat":"030007","count":5},{"istat":"030019","count":5},{"istat":"030065","count":5}],"top_origini":[{"istat":"030116","count":8},{"istat":"030006","count":1},{"istat":"030113","count":1}]}}