{"_etl_version":"0.1.0","_source":"ISTAT - Matrice pendolarismo per lavoro 2021","_source_url":"https://esploradati.istat.it/databrowser/DWL/PERMPOP/MATPEN/matrix_pendoLAVORO_2021.zip","_license":"CC BY 3.0 IT","_anno_rilevazione":2021,"_motivo_spostamento":"lavoro","_generated_at":"2026-05-16T14:52:45+00:00","kpi":{"uscenti_totali":2863,"entranti_totali":1944,"saldo_netto":-919,"auto_contenimento_pct":38.9,"n_destinazioni":141,"n_origini":124,"top_destinazioni":[{"istat":"030049","count":972},{"istat":"027034","count":354},{"istat":"030129","count":130},{"istat":"027029","count":115},{"istat":"030075","count":95},{"istat":"030100","count":92},{"istat":"030097","count":89},{"istat":"030188","count":81},{"istat":"027016","count":70},{"istat":"030082","count":50}],"top_origini":[{"istat":"027034","count":310},{"istat":"027029","count":169},{"istat":"030097","count":138},{"istat":"030188","count":135},{"istat":"030049","count":133},{"istat":"030069","count":106},{"istat":"027016","count":75},{"istat":"030082","count":68},{"istat":"030064","count":57},{"istat":"030129","count":53}]}}