{"_etl_version":"0.1.0","_source":"ISTAT - Matrice pendolarismo per lavoro 2021","_source_url":"https://esploradati.istat.it/databrowser/DWL/PERMPOP/MATPEN/matrix_pendoLAVORO_2021.zip","_license":"CC BY 3.0 IT","_anno_rilevazione":2021,"_motivo_spostamento":"lavoro","_generated_at":"2026-05-16T14:52:45+00:00","kpi":{"uscenti_totali":1033,"entranti_totali":761,"saldo_netto":-272,"auto_contenimento_pct":23.9,"n_destinazioni":85,"n_origini":73,"top_destinazioni":[{"istat":"030027","count":237},{"istat":"030129","count":172},{"istat":"093041","count":61},{"istat":"030031","count":46},{"istat":"030058","count":42},{"istat":"030099","count":42},{"istat":"093044","count":37},{"istat":"030037","count":34},{"istat":"030057","count":25},{"istat":"030118","count":25}],"top_origini":[{"istat":"030027","count":232},{"istat":"030129","count":65},{"istat":"030009","count":49},{"istat":"030058","count":46},{"istat":"030039","count":25},{"istat":"030031","count":23},{"istat":"030057","count":18},{"istat":"030130","count":17},{"istat":"030015","count":16},{"istat":"030072","count":15}]}}