{"_etl_version":"0.1.0","_source":"ISTAT - Matrice pendolarismo per lavoro 2021","_source_url":"https://esploradati.istat.it/databrowser/DWL/PERMPOP/MATPEN/matrix_pendoLAVORO_2021.zip","_license":"CC BY 3.0 IT","_anno_rilevazione":2021,"_motivo_spostamento":"lavoro","_generated_at":"2026-05-16T14:52:45+00:00","kpi":{"uscenti_totali":1535,"entranti_totali":656,"saldo_netto":-879,"auto_contenimento_pct":21.8,"n_destinazioni":50,"n_origini":31,"top_destinazioni":[{"istat":"099002","count":340},{"istat":"041044","count":261},{"istat":"041019","count":243},{"istat":"099017","count":190},{"istat":"099014","count":86},{"istat":"041065","count":77},{"istat":"099005","count":68},{"istat":"099013","count":58},{"istat":"041068","count":31},{"istat":"041036","count":20}],"top_origini":[{"istat":"099002","count":136},{"istat":"041044","count":122},{"istat":"041019","count":108},{"istat":"099017","count":94},{"istat":"041065","count":44},{"istat":"099005","count":26},{"istat":"041068","count":21},{"istat":"099016","count":19},{"istat":"099013","count":15},{"istat":"041013","count":10}]}}