{"_etl_version":"0.1.0","_source":"ISTAT - Matrice pendolarismo per lavoro 2021","_source_url":"https://esploradati.istat.it/databrowser/DWL/PERMPOP/MATPEN/matrix_pendoLAVORO_2021.zip","_license":"CC BY 3.0 IT","_anno_rilevazione":2021,"_motivo_spostamento":"lavoro","_generated_at":"2026-05-16T14:52:45+00:00","kpi":{"uscenti_totali":1327,"entranti_totali":369,"saldo_netto":-958,"auto_contenimento_pct":21.1,"n_destinazioni":61,"n_origini":39,"top_destinazioni":[{"istat":"050029","count":372},{"istat":"050026","count":124},{"istat":"050025","count":104},{"istat":"050028","count":77},{"istat":"050032","count":75},{"istat":"050040","count":58},{"istat":"050033","count":53},{"istat":"050004","count":48},{"istat":"050005","count":39},{"istat":"050008","count":37}],"top_origini":[{"istat":"050029","count":69},{"istat":"050025","count":42},{"istat":"050005","count":37},{"istat":"050036","count":33},{"istat":"050032","count":22},{"istat":"050028","count":20},{"istat":"050022","count":14},{"istat":"050040","count":14},{"istat":"050004","count":12},{"istat":"050008","count":11}]}}