{"_etl_version":"0.1.0","_source":"ISTAT - Matrice pendolarismo per lavoro 2021","_source_url":"https://esploradati.istat.it/databrowser/DWL/PERMPOP/MATPEN/matrix_pendoLAVORO_2021.zip","_license":"CC BY 3.0 IT","_anno_rilevazione":2021,"_motivo_spostamento":"lavoro","_generated_at":"2026-05-16T14:52:45+00:00","kpi":{"uscenti_totali":79,"entranti_totali":54,"saldo_netto":-25,"auto_contenimento_pct":48.0,"n_destinazioni":13,"n_origini":17,"top_destinazioni":[{"istat":"058091","count":17},{"istat":"057002","count":15},{"istat":"057059","count":14},{"istat":"057057","count":10},{"istat":"057017","count":6},{"istat":"057016","count":3},{"istat":"057025","count":3},{"istat":"066049","count":3},{"istat":"054023","count":2},{"istat":"057031","count":2}],"top_origini":[{"istat":"057002","count":7},{"istat":"057017","count":7},{"istat":"057057","count":7},{"istat":"057059","count":7},{"istat":"057003","count":5},{"istat":"057015","count":4},{"istat":"066056","count":4},{"istat":"058091","count":3},{"istat":"058065","count":2},{"istat":"057008","count":1}]}}