{"_etl_version":"0.1.0","_source":"ISTAT - Matrice pendolarismo per lavoro 2021","_source_url":"https://esploradati.istat.it/databrowser/DWL/PERMPOP/MATPEN/matrix_pendoLAVORO_2021.zip","_license":"CC BY 3.0 IT","_anno_rilevazione":2021,"_motivo_spostamento":"lavoro","_generated_at":"2026-05-16T14:52:45+00:00","kpi":{"uscenti_totali":172,"entranti_totali":101,"saldo_netto":-71,"auto_contenimento_pct":22.2,"n_destinazioni":20,"n_origini":24,"top_destinazioni":[{"istat":"058091","count":59},{"istat":"066062","count":22},{"istat":"066025","count":19},{"istat":"058104","count":15},{"istat":"058010","count":9},{"istat":"058103","count":6},{"istat":"058006","count":5},{"istat":"066080","count":5},{"istat":"058113","count":4},{"istat":"066067","count":4}],"top_origini":[{"istat":"058103","count":12},{"istat":"058091","count":9},{"istat":"066025","count":8},{"istat":"058104","count":7},{"istat":"058109","count":7},{"istat":"058092","count":6},{"istat":"066062","count":6},{"istat":"058006","count":5},{"istat":"058055","count":5},{"istat":"066067","count":5}]}}