{"_etl_version":"0.1.0","_source":"ISTAT - Matrice pendolarismo per lavoro 2021","_source_url":"https://esploradati.istat.it/databrowser/DWL/PERMPOP/MATPEN/matrix_pendoLAVORO_2021.zip","_license":"CC BY 3.0 IT","_anno_rilevazione":2021,"_motivo_spostamento":"lavoro","_generated_at":"2026-05-16T14:52:45+00:00","kpi":{"uscenti_totali":989,"entranti_totali":597,"saldo_netto":-392,"auto_contenimento_pct":33.8,"n_destinazioni":99,"n_origini":66,"top_destinazioni":[{"istat":"061082","count":145},{"istat":"061075","count":120},{"istat":"061022","count":105},{"istat":"063049","count":99},{"istat":"061048","count":48},{"istat":"062001","count":46},{"istat":"061049","count":34},{"istat":"062032","count":26},{"istat":"058091","count":25},{"istat":"063001","count":23}],"top_origini":[{"istat":"061082","count":148},{"istat":"061075","count":144},{"istat":"062001","count":40},{"istat":"061048","count":23},{"istat":"062032","count":20},{"istat":"062043","count":20},{"istat":"061022","count":19},{"istat":"061028","count":15},{"istat":"062008","count":15},{"istat":"062005","count":12}]}}