{"_etl_version":"0.1.0","_source":"ISTAT - Matrice pendolarismo per lavoro 2021","_source_url":"https://esploradati.istat.it/databrowser/DWL/PERMPOP/MATPEN/matrix_pendoLAVORO_2021.zip","_license":"CC BY 3.0 IT","_anno_rilevazione":2021,"_motivo_spostamento":"lavoro","_generated_at":"2026-05-16T14:52:45+00:00","kpi":{"uscenti_totali":585,"entranti_totali":900,"saldo_netto":315,"auto_contenimento_pct":51.3,"n_destinazioni":72,"n_origini":82,"top_destinazioni":[{"istat":"061022","count":70},{"istat":"061089","count":57},{"istat":"061017","count":56},{"istat":"058091","count":32},{"istat":"061091","count":31},{"istat":"061015","count":28},{"istat":"061042","count":23},{"istat":"061083","count":23},{"istat":"063049","count":23},{"istat":"061060","count":21}],"top_origini":[{"istat":"061089","count":219},{"istat":"061017","count":80},{"istat":"061052","count":68},{"istat":"061091","count":65},{"istat":"061010","count":49},{"istat":"061042","count":33},{"istat":"061060","count":30},{"istat":"061100","count":28},{"istat":"063062","count":25},{"istat":"063034","count":21}]}}