{"_etl_version":"0.1.0","_source":"ISTAT - Matrice pendolarismo per lavoro 2021","_source_url":"https://esploradati.istat.it/databrowser/DWL/PERMPOP/MATPEN/matrix_pendoLAVORO_2021.zip","_license":"CC BY 3.0 IT","_anno_rilevazione":2021,"_motivo_spostamento":"lavoro","_generated_at":"2026-05-16T14:52:45+00:00","kpi":{"uscenti_totali":1314,"entranti_totali":706,"saldo_netto":-608,"auto_contenimento_pct":50.4,"n_destinazioni":138,"n_origini":89,"top_destinazioni":[{"istat":"062008","count":142},{"istat":"061022","count":128},{"istat":"063049","count":95},{"istat":"062038","count":77},{"istat":"062027","count":71},{"istat":"062028","count":57},{"istat":"061048","count":55},{"istat":"062001","count":52},{"istat":"062043","count":44},{"istat":"062048","count":43}],"top_origini":[{"istat":"062040","count":59},{"istat":"062001","count":58},{"istat":"061048","count":49},{"istat":"062027","count":49},{"istat":"062038","count":43},{"istat":"062028","count":37},{"istat":"061022","count":36},{"istat":"062043","count":30},{"istat":"062035","count":27},{"istat":"062074","count":20}]}}