{"_etl_version":"0.1.0","_source":"ISTAT - Matrice pendolarismo per lavoro 2021","_source_url":"https://esploradati.istat.it/databrowser/DWL/PERMPOP/MATPEN/matrix_pendoLAVORO_2021.zip","_license":"CC BY 3.0 IT","_anno_rilevazione":2021,"_motivo_spostamento":"lavoro","_generated_at":"2026-05-16T14:52:45+00:00","kpi":{"uscenti_totali":300,"entranti_totali":210,"saldo_netto":-90,"auto_contenimento_pct":32.9,"n_destinazioni":59,"n_origini":55,"top_destinazioni":[{"istat":"062008","count":53},{"istat":"062070","count":27},{"istat":"062074","count":18},{"istat":"063049","count":18},{"istat":"062038","count":17},{"istat":"062039","count":15},{"istat":"061023","count":14},{"istat":"062068","count":12},{"istat":"061022","count":10},{"istat":"062073","count":10}],"top_origini":[{"istat":"062070","count":34},{"istat":"062039","count":16},{"istat":"062074","count":15},{"istat":"062075","count":14},{"istat":"061075","count":8},{"istat":"062073","count":8},{"istat":"062043","count":7},{"istat":"061082","count":6},{"istat":"062008","count":6},{"istat":"062077","count":6}]}}