{"_etl_version":"0.1.0","_source":"ISTAT - Matrice pendolarismo per lavoro 2021","_source_url":"https://esploradati.istat.it/databrowser/DWL/PERMPOP/MATPEN/matrix_pendoLAVORO_2021.zip","_license":"CC BY 3.0 IT","_anno_rilevazione":2021,"_motivo_spostamento":"lavoro","_generated_at":"2026-05-16T14:52:45+00:00","kpi":{"uscenti_totali":653,"entranti_totali":313,"saldo_netto":-340,"auto_contenimento_pct":25.4,"n_destinazioni":61,"n_origini":50,"top_destinazioni":[{"istat":"064008","count":268},{"istat":"064034","count":50},{"istat":"064101","count":30},{"istat":"063049","count":28},{"istat":"064006","count":27},{"istat":"064121","count":26},{"istat":"064054","count":25},{"istat":"064075","count":23},{"istat":"064049","count":22},{"istat":"065052","count":13}],"top_origini":[{"istat":"064008","count":78},{"istat":"064034","count":78},{"istat":"064054","count":15},{"istat":"064121","count":15},{"istat":"064001","count":14},{"istat":"064049","count":13},{"istat":"064006","count":11},{"istat":"064059","count":8},{"istat":"065056","count":7},{"istat":"064057","count":5}]}}