{"_etl_version":"0.1.0","_source":"ISTAT - Matrice pendolarismo per lavoro 2021","_source_url":"https://esploradati.istat.it/databrowser/DWL/PERMPOP/MATPEN/matrix_pendoLAVORO_2021.zip","_license":"CC BY 3.0 IT","_anno_rilevazione":2021,"_motivo_spostamento":"lavoro","_generated_at":"2026-05-16T14:52:45+00:00","kpi":{"uscenti_totali":2964,"entranti_totali":1593,"saldo_netto":-1371,"auto_contenimento_pct":19.8,"n_destinazioni":93,"n_origini":125,"top_destinazioni":[{"istat":"065116","count":935},{"istat":"065099","count":580},{"istat":"065014","count":419},{"istat":"065158","count":323},{"istat":"065050","count":171},{"istat":"065073","count":89},{"istat":"063049","count":65},{"istat":"065056","count":33},{"istat":"065037","count":20},{"istat":"065025","count":18}],"top_origini":[{"istat":"065099","count":249},{"istat":"065116","count":202},{"istat":"065158","count":174},{"istat":"065014","count":171},{"istat":"065073","count":135},{"istat":"065056","count":62},{"istat":"065050","count":43},{"istat":"065082","count":35},{"istat":"065037","count":28},{"istat":"065022","count":24}]}}