{"_etl_version":"0.1.0","_source":"ISTAT - Matrice pendolarismo per lavoro 2021","_source_url":"https://esploradati.istat.it/databrowser/DWL/PERMPOP/MATPEN/matrix_pendoLAVORO_2021.zip","_license":"CC BY 3.0 IT","_anno_rilevazione":2021,"_motivo_spostamento":"lavoro","_generated_at":"2026-05-16T14:52:45+00:00","kpi":{"uscenti_totali":4530,"entranti_totali":8914,"saldo_netto":4384,"auto_contenimento_pct":76.3,"n_destinazioni":137,"n_origini":195,"top_destinazioni":[{"istat":"067011","count":575},{"istat":"067030","count":523},{"istat":"067025","count":412},{"istat":"067028","count":285},{"istat":"067008","count":211},{"istat":"067005","count":159},{"istat":"068028","count":145},{"istat":"067037","count":140},{"istat":"066049","count":131},{"istat":"067044","count":126}],"top_origini":[{"istat":"067006","count":677},{"istat":"067037","count":653},{"istat":"067028","count":627},{"istat":"067025","count":605},{"istat":"067008","count":598},{"istat":"067011","count":590},{"istat":"067043","count":438},{"istat":"067044","count":355},{"istat":"067030","count":260},{"istat":"067032","count":232}]}}