{"_etl_version":"0.1.0","_source":"ISTAT - Matrice pendolarismo per lavoro 2021","_source_url":"https://esploradati.istat.it/databrowser/DWL/PERMPOP/MATPEN/matrix_pendoLAVORO_2021.zip","_license":"CC BY 3.0 IT","_anno_rilevazione":2021,"_motivo_spostamento":"lavoro","_generated_at":"2026-05-16T14:52:45+00:00","kpi":{"uscenti_totali":4272,"entranti_totali":3047,"saldo_netto":-1225,"auto_contenimento_pct":50.2,"n_destinazioni":105,"n_origini":97,"top_destinazioni":[{"istat":"067041","count":653},{"istat":"067025","count":646},{"istat":"067035","count":437},{"istat":"067030","count":415},{"istat":"067011","count":241},{"istat":"067029","count":233},{"istat":"067004","count":219},{"istat":"067032","count":199},{"istat":"068028","count":169},{"istat":"067044","count":115}],"top_origini":[{"istat":"067035","count":683},{"istat":"067025","count":318},{"istat":"067029","count":289},{"istat":"067032","count":271},{"istat":"067004","count":269},{"istat":"067041","count":140},{"istat":"067040","count":122},{"istat":"067011","count":119},{"istat":"067030","count":91},{"istat":"067015","count":63}]}}