{"_etl_version":"0.1.0","_source":"ISTAT - Matrice pendolarismo per lavoro 2021","_source_url":"https://esploradati.istat.it/databrowser/DWL/PERMPOP/MATPEN/matrix_pendoLAVORO_2021.zip","_license":"CC BY 3.0 IT","_anno_rilevazione":2021,"_motivo_spostamento":"lavoro","_generated_at":"2026-05-16T14:52:45+00:00","kpi":{"uscenti_totali":235,"entranti_totali":57,"saldo_netto":-178,"auto_contenimento_pct":30.3,"n_destinazioni":26,"n_origini":17,"top_destinazioni":[{"istat":"070006","count":150},{"istat":"070003","count":13},{"istat":"070007","count":11},{"istat":"070002","count":10},{"istat":"070059","count":7},{"istat":"070078","count":7},{"istat":"070080","count":5},{"istat":"070028","count":4},{"istat":"070076","count":4},{"istat":"070084","count":4}],"top_origini":[{"istat":"070006","count":14},{"istat":"070002","count":9},{"istat":"070003","count":5},{"istat":"070023","count":5},{"istat":"070049","count":4},{"istat":"070059","count":3},{"istat":"070078","count":3},{"istat":"070084","count":3},{"istat":"058091","count":2},{"istat":"070012","count":2}]}}