{"_etl_version":"0.1.0","_source":"ISTAT - Matrice pendolarismo per lavoro 2021","_source_url":"https://esploradati.istat.it/databrowser/DWL/PERMPOP/MATPEN/matrix_pendoLAVORO_2021.zip","_license":"CC BY 3.0 IT","_anno_rilevazione":2021,"_motivo_spostamento":"lavoro","_generated_at":"2026-05-16T14:52:45+00:00","kpi":{"uscenti_totali":270,"entranti_totali":625,"saldo_netto":355,"auto_contenimento_pct":39.7,"n_destinazioni":35,"n_origini":60,"top_destinazioni":[{"istat":"075039","count":34},{"istat":"075035","count":32},{"istat":"075061","count":30},{"istat":"075088","count":22},{"istat":"075078","count":19},{"istat":"075095","count":16},{"istat":"075054","count":11},{"istat":"075005","count":9},{"istat":"075016","count":9},{"istat":"075081","count":9}],"top_origini":[{"istat":"075064","count":63},{"istat":"075088","count":57},{"istat":"075086","count":52},{"istat":"075078","count":34},{"istat":"075054","count":33},{"istat":"075049","count":31},{"istat":"075002","count":24},{"istat":"075046","count":24},{"istat":"075061","count":24},{"istat":"075005","count":22}]}}