{"_etl_version":"0.1.0","_source":"ISTAT - Matrice pendolarismo per lavoro 2021","_source_url":"https://esploradati.istat.it/databrowser/DWL/PERMPOP/MATPEN/matrix_pendoLAVORO_2021.zip","_license":"CC BY 3.0 IT","_anno_rilevazione":2021,"_motivo_spostamento":"lavoro","_generated_at":"2026-05-16T14:52:45+00:00","kpi":{"uscenti_totali":840,"entranti_totali":417,"saldo_netto":-423,"auto_contenimento_pct":45.3,"n_destinazioni":48,"n_origini":52,"top_destinazioni":[{"istat":"080061","count":213},{"istat":"080028","count":78},{"istat":"080038","count":74},{"istat":"080063","count":57},{"istat":"080003","count":42},{"istat":"080049","count":40},{"istat":"080065","count":34},{"istat":"080093","count":33},{"istat":"080069","count":28},{"istat":"080071","count":26}],"top_origini":[{"istat":"080061","count":112},{"istat":"080003","count":49},{"istat":"080028","count":29},{"istat":"080071","count":28},{"istat":"080049","count":27},{"istat":"080037","count":21},{"istat":"080093","count":15},{"istat":"080046","count":13},{"istat":"080069","count":10},{"istat":"080032","count":8}]}}