{"_etl_version":"0.1.0","_source":"ISTAT - Matrice pendolarismo per lavoro 2021","_source_url":"https://esploradati.istat.it/databrowser/DWL/PERMPOP/MATPEN/matrix_pendoLAVORO_2021.zip","_license":"CC BY 3.0 IT","_anno_rilevazione":2021,"_motivo_spostamento":"lavoro","_generated_at":"2026-05-16T14:52:45+00:00","kpi":{"uscenti_totali":395,"entranti_totali":176,"saldo_netto":-219,"auto_contenimento_pct":45.7,"n_destinazioni":15,"n_origini":14,"top_destinazioni":[{"istat":"081021","count":117},{"istat":"081005","count":74},{"istat":"081007","count":42},{"istat":"081008","count":42},{"istat":"081022","count":39},{"istat":"081020","count":38},{"istat":"082053","count":18},{"istat":"081003","count":7},{"istat":"081013","count":6},{"istat":"081001","count":5}],"top_origini":[{"istat":"081022","count":49},{"istat":"081008","count":35},{"istat":"081021","count":31},{"istat":"081007","count":21},{"istat":"081001","count":10},{"istat":"081005","count":10},{"istat":"081013","count":6},{"istat":"081020","count":5},{"istat":"081003","count":4},{"istat":"081019","count":1}]}}