{"_etl_version":"0.1.0","_source":"ISTAT - Matrice pendolarismo per lavoro 2021","_source_url":"https://esploradati.istat.it/databrowser/DWL/PERMPOP/MATPEN/matrix_pendoLAVORO_2021.zip","_license":"CC BY 3.0 IT","_anno_rilevazione":2021,"_motivo_spostamento":"lavoro","_generated_at":"2026-05-16T14:52:45+00:00","kpi":{"uscenti_totali":438,"entranti_totali":117,"saldo_netto":-321,"auto_contenimento_pct":32.9,"n_destinazioni":24,"n_origini":13,"top_destinazioni":[{"istat":"082054","count":158},{"istat":"082053","count":118},{"istat":"082007","count":51},{"istat":"082021","count":25},{"istat":"082071","count":16},{"istat":"081001","count":13},{"istat":"082031","count":11},{"istat":"082013","count":9},{"istat":"082038","count":7},{"istat":"081005","count":6}],"top_origini":[{"istat":"082054","count":50},{"istat":"082053","count":21},{"istat":"082007","count":19},{"istat":"082071","count":5},{"istat":"081001","count":4},{"istat":"082013","count":4},{"istat":"082064","count":4},{"istat":"082021","count":3},{"istat":"082049","count":2},{"istat":"082079","count":2}]}}