{"_etl_version":"0.1.0","_source":"ISTAT - Matrice pendolarismo per lavoro 2021","_source_url":"https://esploradati.istat.it/databrowser/DWL/PERMPOP/MATPEN/matrix_pendoLAVORO_2021.zip","_license":"CC BY 3.0 IT","_anno_rilevazione":2021,"_motivo_spostamento":"lavoro","_generated_at":"2026-05-16T14:52:45+00:00","kpi":{"uscenti_totali":1640,"entranti_totali":740,"saldo_netto":-900,"auto_contenimento_pct":37.1,"n_destinazioni":39,"n_origini":37,"top_destinazioni":[{"istat":"082006","count":700},{"istat":"082053","count":646},{"istat":"082023","count":57},{"istat":"082070","count":36},{"istat":"082004","count":30},{"istat":"082048","count":25},{"istat":"082035","count":22},{"istat":"082079","count":22},{"istat":"082021","count":14},{"istat":"082073","count":13}],"top_origini":[{"istat":"082006","count":353},{"istat":"082023","count":107},{"istat":"082053","count":85},{"istat":"082004","count":39},{"istat":"082035","count":28},{"istat":"082079","count":18},{"istat":"082048","count":14},{"istat":"082070","count":14},{"istat":"082073","count":13},{"istat":"082014","count":7}]}}