{"_etl_version":"0.1.0","_source":"ISTAT - Matrice pendolarismo per lavoro 2021","_source_url":"https://esploradati.istat.it/databrowser/DWL/PERMPOP/MATPEN/matrix_pendoLAVORO_2021.zip","_license":"CC BY 3.0 IT","_anno_rilevazione":2021,"_motivo_spostamento":"lavoro","_generated_at":"2026-05-16T14:52:45+00:00","kpi":{"uscenti_totali":378,"entranti_totali":65,"saldo_netto":-313,"auto_contenimento_pct":27.4,"n_destinazioni":36,"n_origini":11,"top_destinazioni":[{"istat":"095038","count":206},{"istat":"095018","count":36},{"istat":"095050","count":19},{"istat":"095047","count":16},{"istat":"095043","count":14},{"istat":"095059","count":9},{"istat":"095027","count":8},{"istat":"095006","count":6},{"istat":"095065","count":6},{"istat":"092009","count":5}],"top_origini":[{"istat":"095038","count":19},{"istat":"095018","count":11},{"istat":"095043","count":7},{"istat":"095050","count":7},{"istat":"095065","count":7},{"istat":"095011","count":6},{"istat":"095047","count":2},{"istat":"095066","count":2},{"istat":"095074","count":2},{"istat":"095025","count":1}]}}