{"_etl_version":"0.1.0","_source":"ISTAT - Matrice pendolarismo per lavoro 2021","_source_url":"https://esploradati.istat.it/databrowser/DWL/PERMPOP/MATPEN/matrix_pendoLAVORO_2021.zip","_license":"CC BY 3.0 IT","_anno_rilevazione":2021,"_motivo_spostamento":"lavoro","_generated_at":"2026-05-16T14:52:45+00:00","kpi":{"uscenti_totali":393,"entranti_totali":175,"saldo_netto":-218,"auto_contenimento_pct":39.3,"n_destinazioni":33,"n_origini":29,"top_destinazioni":[{"istat":"102047","count":214},{"istat":"102003","count":33},{"istat":"102044","count":18},{"istat":"102017","count":13},{"istat":"102030","count":11},{"istat":"102049","count":11},{"istat":"102026","count":9},{"istat":"102048","count":9},{"istat":"079023","count":7},{"istat":"102043","count":6}],"top_origini":[{"istat":"102003","count":34},{"istat":"102047","count":28},{"istat":"102017","count":9},{"istat":"102027","count":9},{"istat":"102012","count":8},{"istat":"102009","count":7},{"istat":"102033","count":7},{"istat":"102049","count":7},{"istat":"102015","count":6},{"istat":"102031","count":6}]}}